basefund.py
datasource_akpack.py
datasource_ths.py
datasource_ttjj.py
enhanceezqq.py
enhanceezqq-1.0.2.6.dist-info/METADATA
enhanceezqq-1.0.2.6.dist-info/WHEEL
enhanceezqq-1.0.2.6.dist-info/top_level.txt
enhanceezqq-1.0.2.6.dist-info/RECORD
